timer/__init__.py
timer/cuca.wav
timer/main.py
command_line_timer-0.1.1.dist-info/LICENSE
command_line_timer-0.1.1.dist-info/METADATA
command_line_timer-0.1.1.dist-info/WHEEL
command_line_timer-0.1.1.dist-info/entry_points.txt
command_line_timer-0.1.1.dist-info/top_level.txt
command_line_timer-0.1.1.dist-info/RECORD
