Metadata-Version: 2.1
Name: command-line-timer
Version: 0.1.1
Summary: count down from HH:MM:SS and then sound an alarm (la cucaracha!).
Home-page: https://gitlab.com/shindagger/command-line-timer
Author: Andy Klier
Author-email: andyklier@gmail.com
License: UNKNOWN
Platform: UNKNOWN
Classifier: Programming Language :: Python :: 3
Classifier: License :: OSI Approved :: MIT License
Classifier: Operating System :: OS Independent
Requires-Dist: setuptools
Requires-Dist: pygame
